fastapi_lsoft/__init__.py
fastapi_lsoft/depends/__init__.py
fastapi_lsoft/middleware/__init__.py
fastapi_lsoft-1.2.0.dist-info/METADATA
fastapi_lsoft-1.2.0.dist-info/WHEEL
fastapi_lsoft-1.2.0.dist-info/RECORD
