Metadata-Version: 2.4
Name: fastapi-lsoft
Version: 1.2.0
Summary: Add your description here
Requires-Python: >=3.12
Requires-Dist: fastapi>=0.104.1
